Workbook

Sheet Dashboard Executivo
B2: PAINEL EXECUTIVO - GESTAO DE TRAFEGO PAGO
B4: Investimento Total | D4: Faturamento Total | F4: Lucro Bruto | H4: ROAS Medio | J4: Metas Desejadas
B5: =SUM('Controle Diario'!B) -> #NAME? | D5: =SUM('Controle Diario'!I) -> #NAME? | F5: =D5-B5 -> #NAME? | H5: =IF(B5>0, D5/B5, 0) -> #NAME? | J5: Meta ROAS | K5: 2
J6: Meta CPA Max | K6: 20
B7: Compras Totais | D7: CPA Medio | F7: Ticket Medio | H7: Cliques Totais
B8: =SUM('Controle Diario'!H) -> #NAME? | D8: =IF(B8>0, B5/B8, 0) -> #NAME? | F8: =IF(B8>0, D5/B8, 0) -> #NAME? | H8: =SUM('Controle Diario'!E) -> #NAME? | J8: Status ROAS | K8: =IF(H5<1, _xlfn.UNICHAR(128992) & " Acao", IF(H5<K5, _xlfn.UNICHAR(128993) & " Atencao", _xlfn.UNICHAR(128994) & " OK")) -> #NAME?
J9: Status CPA | K9: =IF(D8=0, "-", IF(D8>K6*1.5, _xlfn.UNICHAR(128992) & " Acao", IF(D8>K6, _xlfn.UNICHAR(128993) & " Atencao", _xlfn.UNICHAR(128994) & " OK"))) -> #NAME?
B10: Finalizacoes de Compra | D10: Tx. Landing -> Checkout | F10: Tx. Checkout -> Compra
B11: =SUM('Controle Diario'!G) -> #NAME? | D11: =IF(SUM('Controle Diario'!F)>0, B11/SUM('Controle Diario'!F), 0) -> #NAME? | F11: =IF(B11>0, B8/B11, 0) -> #NAME?

Sheet Controle Diario
A2: CONTROLE DIARIO DE TRAFEGO PAGO (PREENCHIMENTO DIARIO)
A4: Data | B4: Valor Investido | C4: Impressoes | D4: Alcance | E4: Cliques no Link | F4: Visualizacoes da Pagina | G4: Finalizacoes de Compra | H4: Compras | I4: Faturamento | J4: CPC | K4: CTR | L4: CPA | M4: ROAS | N4: Taxa Landing -> Checkout | O4: Taxa Checkout -> Compra | P4: Observacoes
A5: 46301 | B5: 50 | C5: 5000 | D5: 4200 | E5: 100 | F5: 75 | G5: 12 | H5: 2 | I5: 94 | J5: =IF(A5="","",IF(E5>0, B5/E5, 0)) -> 0.5 | K5: =IF(A5="","",IF(C5>0, E5/C5, 0)) -> 0.02 | L5: =IF(A5="","",IF(H5>0, B5/H5, 0)) -> 25 | M5: =IF(A5="","",IF(B5>0, I5/B5, 0)) -> 1.88 | N5: =IF(A5="","",IF(F5>0, G5/F5, 0)) -> 0.16 | O5: =IF(A5="","",IF(G5>0, H5/G5, 0)) -> 0.16666667 | P5: Campanha 1 ativa
A6: 46332 | B6: 60 | C6: 6000 | D6: 5100 | E6: 120 | F6: 90 | G6: 15 | H6: 3 | I6: 141 | J6: =IF(A6="","",IF(E6>0, B6/E6, 0)) -> 0.5 | K6: =IF(A6="","",IF(C6>0, E6/C6, 0)) -> 0.02 | L6: =IF(A6="","",IF(H6>0, B6/H6, 0)) -> 20 | M6: =IF(A6="","",IF(B6>0, I6/B6, 0)) -> 2.35 | N6: =IF(A6="","",IF(F6>0, G6/F6, 0)) -> 0.16666667 | O6: =IF(A6="","",IF(G6>0, H6/G6, 0)) -> 0.2 | P6: Subiu orcamento
A7: 46362 | B7: 75 | C7: 7500 | D7: 6300 | E7: 130 | F7: 95 | G7: 18 | H7: 2 | I7: 94 | J7: =IF(A7="","",IF(E7>0, B7/E7, 0)) -> 0.57692308 | K7: =IF(A7="","",IF(C7>0, E7/C7, 0)) -> 0.017333333 | L7: =IF(A7="","",IF(H7>0, B7/H7, 0)) -> 37.5 | M7: =IF(A7="","",IF(B7>0, I7/B7, 0)) -> 1.2533333 | N7: =IF(A7="","",IF(F7>0, G7/F7, 0)) -> 0.18947368 | O7: =IF(A7="","",IF(G7>0, H7/G7, 0)) -> 0.11111111 | P7: CPA subiu um pouco
A8: 13/06/2026 | B8: 75 | C8: 7800 | D8: 6500 | E8: 140 | F8: 110 | G8: 8 | H8: 1 | I8: 47 | J8: =IF(A8="","",IF(E8>0, B8/E8, 0)) -> 0.53571429 | K8: =IF(A8="","",IF(C8>0, E8/C8, 0)) -> 0.017948718 | L8: =IF(A8="","",IF(H8>0, B8/H8, 0)) -> 75 | M8: =IF(A8="","",IF(B8>0, I8/B8, 0)) -> 0.62666667 | N8: =IF(A8="","",IF(F8>0, G8/F8, 0)) -> 0.072727273 | O8: =IF(A8="","",IF(G8>0, H8/G8, 0)) -> 0.125 | P8: Queda na conversao
A9: 14/06/2026 | B9: 75 | C9: 8000 | D9: 6800 | E9: 160 | F9: 125 | G9: 22 | H9: 4 | I9: 188 | J9: =IF(A9="","",IF(E9>0, B9/E9, 0)) -> 0.46875 | K9: =IF(A9="","",IF(C9>0, E9/C9, 0)) -> 0.02 | L9: =IF(A9="","",IF(H9>0, B9/H9, 0)) -> 18.75 | M9: =IF(A9="","",IF(B9>0, I9/B9, 0)) -> 2.5066667 | N9: =IF(A9="","",IF(F9>0, G9/F9, 0)) -> 0.176 | O9: =IF(A9="","",IF(G9>0, H9/G9, 0)) -> 0.18181818 | P9: Recuperacao de boletos
A10: 15/06/2026 | B10: 100 | C10: 10000 | D10: 8500 | E10: 210 | F10: 160 | G10: 30 | H10: 5 | I10: 235 | J10: =IF(A10="","",IF(E10>0, B10/E10, 0)) -> 0.47619048 | K10: =IF(A10="","",IF(C10>0, E10/C10, 0)) -> 0.021 | L10: =IF(A10="","",IF(H10>0, B10/H10, 0)) -> 20 | M10: =IF(A10="","",IF(B10>0, I10/B10, 0)) -> 2.35 | N10: =IF(A10="","",IF(F10>0, G10/F10, 0)) -> 0.1875 | O10: =IF(A10="","",IF(G10>0, H10/G10, 0)) -> 0.16666667 | P10: Novo criativo adicionado
A11: 16/06/2026 | B11: 100 | C11: 10500 | D11: 8900 | E11: 220 | F11: 170 | G11: 28 | H11: 6 | I11: 282 | J11: =IF(A11="","",IF(E11>0, B11/E11, 0)) -> 0.45454545 | K11: =IF(A11="","",IF(C11>0, E11/C11, 0)) -> 0.020952381 | L11: =IF(A11="","",IF(H11>0, B11/H11, 0)) -> 16.666667 | M11: =IF(A11="","",IF(B11>0, I11/B11, 0)) -> 2.82 | N11: =IF(A11="","",IF(F11>0, G11/F11, 0)) -> 0.16470588 | O11: =IF(A11="","",IF(G11>0, H11/G11, 0)) -> 0.21428571 | P11: Melhor dia do mes
A12: 17/06/2026 | B12: 120 | C12: 12000 | D12: 9900 | E12: 240 | F12: 185 | G12: 25 | H12: 3 | I12: 141 | J12: =IF(A12="","",IF(E12>0, B12/E12, 0)) -> 0.5 | K12: =IF(A12="","",IF(C12>0, E12/C12, 0)) -> 0.02 | L12: =IF(A12="","",IF(H12>0, B12/H12, 0)) -> 40 | M12: =IF(A12="","",IF(B12>0, I12/B12, 0)) -> 1.175 | N12: =IF(A12="","",IF(F12>0, G12/F12, 0)) -> 0.13513514 | O12: =IF(A12="","",IF(G12>0, H12/G12, 0)) -> 0.12 | P12: Instabilidade na tarde
A13: 18/06/2026 | B13: 120 | C13: 12500 | D13: 10200 | E13: 250 | F13: 190 | G13: 32 | H13: 5 | I13: 235 | J13: =IF(A13="","",IF(E13>0, B13/E13, 0)) -> 0.48 | K13: =IF(A13="","",IF(C13>0, E13/C13, 0)) -> 0.02 | L13: =IF(A13="","",IF(H13>0, B13/H13, 0)) -> 24 | M13: =IF(A13="","",IF(B13>0, I13/B13, 0)) -> 1.9583333 | N13: =IF(A13="","",IF(F13>0, G13/F13, 0)) -> 0.16842105 | O13: =IF(A13="","",IF(G13>0, H13/G13, 0)) -> 0.15625 | P13: Escalando criativo B
A14: 19/06/2026 | B14: 150 | C14: 15000 | D14: 12000 | E14: 310 | F14: 240 | G14: 45 | H14: 8 | I14: 376 | J14: =IF(A14="","",IF(E14>0, B14/E14, 0)) -> 0.48387097 | K14: =IF(A14="","",IF(C14>0, E14/C14, 0)) -> 0.020666667 | L14: =IF(A14="","",IF(H14>0, B14/H14, 0)) -> 18.75 | M14: =IF(A14="","",IF(B14>0, I14/B14, 0)) -> 2.5066667 | N14: =IF(A14="","",IF(F14>0, G14/F14, 0)) -> 0.1875 | O14: =IF(A14="","",IF(G14>0, H14/G14, 0)) -> 0.17777778 | P14: Excelente performance
J15: =IF(A15="","",IF(E15>0, B15/E15, 0)) | K15: =IF(A15="","",IF(C15>0, E15/C15, 0)) | L15: =IF(A15="","",IF(H15>0, B15/H15, 0)) | M15: =IF(A15="","",IF(B15>0, I15/B15, 0)) | N15: =IF(A15="","",IF(F15>0, G15/F15, 0)) | O15: =IF(A15="","",IF(G15>0, H15/G15, 0))
J16: =IF(A16="","",IF(E16>0, B16/E16, 0)) | K16: =IF(A16="","",IF(C16>0, E16/C16, 0)) | L16: =IF(A16="","",IF(H16>0, B16/H16, 0)) | M16: =IF(A16="","",IF(B16>0, I16/B16, 0)) | N16: =IF(A16="","",IF(F16>0, G16/F16, 0)) | O16: =IF(A16="","",IF(G16>0, H16/G16, 0))
J17: =IF(A17="","",IF(E17>0, B17/E17, 0)) | K17: =IF(A17="","",IF(C17>0, E17/C17, 0)) | L17: =IF(A17="","",IF(H17>0, B17/H17, 0)) | M17: =IF(A17="","",IF(B17>0, I17/B17, 0)) | N17: =IF(A17="","",IF(F17>0, G17/F17, 0)) | O17: =IF(A17="","",IF(G17>0, H17/G17, 0))
J18: =IF(A18="","",IF(E18>0, B18/E18, 0)) | K18: =IF(A18="","",IF(C18>0, E18/C18, 0)) | L18: =IF(A18="","",IF(H18>0, B18/H18, 0)) | M18: =IF(A18="","",IF(B18>0, I18/B18, 0)) | N18: =IF(A18="","",IF(F18>0, G18/F18, 0)) | O18: =IF(A18="","",IF(G18>0, H18/G18, 0))
J19: =IF(A19="","",IF(E19>0, B19/E19, 0)) | K19: =IF(A19="","",IF(C19>0, E19/C19, 0)) | L19: =IF(A19="","",IF(H19>0, B19/H19, 0)) | M19: =IF(A19="","",IF(B19>0, I19/B19, 0)) | N19: =IF(A19="","",IF(F19>0, G19/F19, 0)) | O19: =IF(A19="","",IF(G19>0, H19/G19, 0))
J20: =IF(A20="","",IF(E20>0, B20/E20, 0)) | K20: =IF(A20="","",IF(C20>0, E20/C20, 0)) | L20: =IF(A20="","",IF(H20>0, B20/H20, 0)) | M20: =IF(A20="","",IF(B20>0, I20/B20, 0)) | N20: =IF(A20="","",IF(F20>0, G20/F20, 0)) | O20: =IF(A20="","",IF(G20>0, H20/G20, 0))
J21: =IF(A21="","",IF(E21>0, B21/E21, 0)) | K21: =IF(A21="","",IF(C21>0, E21/C21, 0)) | L21: =IF(A21="","",IF(H21>0, B21/H21, 0)) | M21: =IF(A21="","",IF(B21>0, I21/B21, 0)) | N21: =IF(A21="","",IF(F21>0, G21/F21, 0)) | O21: =IF(A21="","",IF(G21>0, H21/G21, 0))
J22: =IF(A22="","",IF(E22>0, B22/E22, 0)) | K22: =IF(A22="","",IF(C22>0, E22/C22, 0)) | L22: =IF(A22="","",IF(H22>0, B22/H22, 0)) | M22: =IF(A22="","",IF(B22>0, I22/B22, 0)) | N22: =IF(A22="","",IF(F22>0, G22/F22, 0)) | O22: =IF(A22="","",IF(G22>0, H22/G22, 0))
J23: =IF(A23="","",IF(E23>0, B23/E23, 0)) | K23: =IF(A23="","",IF(C23>0, E23/C23, 0)) | L23: =IF(A23="","",IF(H23>0, B23/H23, 0)) | M23: =IF(A23="","",IF(B23>0, I23/B23, 0)) | N23: =IF(A23="","",IF(F23>0, G23/F23, 0)) | O23: =IF(A23="","",IF(G23>0, H23/G23, 0))
J24: =IF(A24="","",IF(E24>0, B24/E24, 0)) | K24: =IF(A24="","",IF(C24>0, E24/C24, 0)) | L24: =IF(A24="","",IF(H24>0, B24/H24, 0)) | M24: =IF(A24="","",IF(B24>0, I24/B24, 0)) | N24: =IF(A24="","",IF(F24>0, G24/F24, 0)) | O24: =IF(A24="","",IF(G24>0, H24/G24, 0))
J25: =IF(A25="","",IF(E25>0, B25/E25, 0)) | K25: =IF(A25="","",IF(C25>0, E25/C25, 0)) | L25: =IF(A25="","",IF(H25>0, B25/H25, 0)) | M25: =IF(A25="","",IF(B25>0, I25/B25, 0)) | N25: =IF(A25="","",IF(F25>0, G25/F25, 0)) | O25: =IF(A25="","",IF(G25>0, H25/G25, 0))
J26: =IF(A26="","",IF(E26>0, B26/E26, 0)) | K26: =IF(A26="","",IF(C26>0, E26/C26, 0)) | L26: =IF(A26="","",IF(H26>0, B26/H26, 0)) | M26: =IF(A26="","",IF(B26>0, I26/B26, 0)) | N26: =IF(A26="","",IF(F26>0, G26/F26, 0)) | O26: =IF(A26="","",IF(G26>0, H26/G26, 0))
... J100: =IF(A100="","",IF(E100>0, B100/E100, 0)) | K100: =IF(A100="","",IF(C100>0, E100/C100, 0)) | L100: =IF(A100="","",IF(H100>0, B100/H100, 0)) | M100: =IF(A100="","",IF(B100>0, I100/B100, 0)) | N100: =IF(A100="","",IF(F100>0, G100/F100, 0)) | O100: =IF(A100="","",IF(G100>0, H100/G100, 0))

Sheet Controle de Criativos
A2: CONTROLE DE CRIATIVOS
A4: Nome do Criativo | B4: Data de Inicio | C4: Status | D4: Valor Investido | E4: Impressoes | F4: Cliques | G4: Finalizacoes de Compra | H4: Compras | I4: CPA | J4: ROAS | K4: Classificacao | L4: Observacoes | O4: Ranking de Criativos
A5: Criativo A - Imagem Oferta | B5: 46301 | C5: Ativo | D5: 300 | E5: 30000 | F5: 600 | G5: 60 | H5: =IF(A5="","",COUNTIFS('Registro de Vendas'!D$5:D$1000, A5)) -> 9 | I5: =IF(A5="","",IF(H5>0, D5/H5, 0)) -> 33.333333 | J5: =IF(A5="","",IF(D5>0, SUMIFS('Registro de Vendas'!B$5:B$1000, 'Registro de Vendas'!D$5:D$1000, A5)/D5, 0)) -> 1.41 | K5: =IF(A5="","",IF(D5=0, "Sem dados", IF(J5>=2, "Excelente", IF(J5>=1.5, "Bom", IF(J5>=1, "Regular", "Ruim"))))) -> Regular | L5: Melhor para cliques de feed | M5: =IF(A5="", 0, J5 + (1000-ROW())/1000000) -> 1.410995 | O5: Posicao | P5: Criativo | Q5: ROAS | R5: CPA
A6: Criativo B - Video Gancho 1 | B6: 46332 | C6: Ativo | D6: 480 | E6: 48000 | F6: 1100 | G6: 95 | H6: =IF(A6="","",COUNTIFS('Registro de Vendas'!D$5:D$1000, A6)) -> 19 | I6: =IF(A6="","",IF(H6>0, D6/H6, 0)) -> 25.263158 | J6: =IF(A6="","",IF(D6>0, SUMIFS('Registro de Vendas'!B$5:B$1000, 'Registro de Vendas'!D$5:D$1000, A6)/D6, 0)) -> 1.8604167 | K6: =IF(A6="","",IF(D6=0, "Sem dados", IF(J6>=2, "Excelente", IF(J6>=1.5, "Bom", IF(J6>=1, "Regular", "Ruim"))))) -> Bom | L6: Gancho muito forte nos 3s | M6: =IF(A6="", 0, J6 + (1000-ROW())/1000000) -> 1.8614107 | O6: =_xlfn.UNICHAR(127942) & " Melhor" -> 🏆 Melhor | P6: =IFERROR(INDEX(A$5:A$100, MATCH(LARGE(M$5:M$100, 1), M$5:M$100, 0)), "-") -> Criativo B - Video Gancho 1 | Q6: =IFERROR(INDEX(J$5:J$100, MATCH(LARGE(M$5:M$100, 1), M$5:M$100, 0)), 0) -> 1.8604167 | R6: =IFERROR(INDEX(I$5:I$100, MATCH(LARGE(M$5:M$100, 1), M$5:M$100, 0)), 0) -> 25.263158
A7: Criativo C - Video Unboxing | B7: 46362 | C7: Ativo | D7: 160 | E7: 15000 | F7: 280 | G7: 28 | H7: =IF(A7="","",COUNTIFS('Registro de Vendas'!D$5:D$1000, A7)) -> 4 | I7: =IF(A7="","",IF(H7>0, D7/H7, 0)) -> 40 | J7: =IF(A7="","",IF(D7>0, SUMIFS('Registro de Vendas'!B$5:B$1000, 'Registro de Vendas'!D$5:D$1000, A7)/D7, 0)) -> 1.175 | K7: =IF(A7="","",IF(D7=0, "Sem dados", IF(J7>=2, "Excelente", IF(J7>=1.5, "Bom", IF(J7>=1, "Regular", "Ruim"))))) -> Regular | L7: Excelente engajamento e retencao | M7: =IF(A7="", 0, J7 + (1000-ROW())/1000000) -> 1.175993 | O7: =_xlfn.UNICHAR(129352) & " Segundo" -> 🥈 Segundo | P7: =IFERROR(INDEX(A$5:A$100, MATCH(LARGE(M$5:M$100, 2), M$5:M$100, 0)), "-") -> Criativo A - Imagem Oferta | Q7: =IFERROR(INDEX(J$5:J$100, MATCH(LARGE(M$5:M$100, 2), M$5:M$100, 0)), 0) -> 1.41 | R7: =IFERROR(INDEX(I$5:I$100, MATCH(LARGE(M$5:M$100, 2), M$5:M$100, 0)), 0) -> 33.333333
A8: Criativo D - Imagem Depoimento | B8: 13/06/2026 | C8: Pausado | D8: 80 | E8: 8000 | F8: 120 | G8: 12 | H8: =IF(A8="","",COUNTIFS('Registro de Vendas'!D$5:D$1000, A8)) -> 1 | I8: =IF(A8="","",IF(H8>0, D8/H8, 0)) -> 80 | J8: =IF(A8="","",IF(D8>0, SUMIFS('Registro de Vendas'!B$5:B$1000, 'Registro de Vendas'!D$5:D$1000, A8)/D8, 0)) -> 0.5875 | K8: =IF(A8="","",IF(D8=0, "Sem dados", IF(J8>=2, "Excelente", IF(J8>=1.5, "Bom", IF(J8>=1, "Regular", "Ruim"))))) -> Ruim | L8: Parado por CPA estourado no dia | M8: =IF(A8="", 0, J8 + (1000-ROW())/1000000) -> 0.588492 | O8: =_xlfn.UNICHAR(129353) & " Terceiro" -> 🥉 Terceiro | P8: =IFERROR(INDEX(A$5:A$100, MATCH(LARGE(M$5:M$100, 3), M$5:M$100, 0)), "-") -> Criativo C - Video Unboxing | Q8: =IFERROR(INDEX(J$5:J$100, MATCH(LARGE(M$5:M$100, 3), M$5:M$100, 0)), 0) -> 1.175 | R8: =IFERROR(INDEX(I$5:I$100, MATCH(LARGE(M$5:M$100, 3), M$5:M$100, 0)), 0) -> 40
A9: Criativo E - Video Promocional | B9: 14/06/2026 | C9: Ativo | D9: 240 | E9: 22000 | F9: 480 | G9: 40 | H9: =IF(A9="","",COUNTIFS('Registro de Vendas'!D$5:D$1000, A9)) -> 6 | I9: =IF(A9="","",IF(H9>0, D9/H9, 0)) -> 40 | J9: =IF(A9="","",IF(D9>0, SUMIFS('Registro de Vendas'!B$5:B$1000, 'Registro de Vendas'!D$5:D$1000, A9)/D9, 0)) -> 1.175 | K9: =IF(A9="","",IF(D9=0, "Sem dados", IF(J9>=2, "Excelente", IF(J9>=1.5, "Bom", IF(J9>=1, "Regular", "Ruim"))))) -> Regular | L9: Visual moderno e dinamico | M9: =IF(A9="", 0, J9 + (1000-ROW())/1000000) -> 1.175991
H10: =IF(A10="","",COUNTIFS('Registro de Vendas'!D$5:D$1000, A10)) | I10: =IF(A10="","",IF(H10>0, D10/H10, 0)) | J10: =IF(A10="","",IF(D10>0, SUMIFS('Registro de Vendas'!B$5:B$1000, 'Registro de Vendas'!D$5:D$1000, A10)/D10, 0)) | K10: =IF(A10="","",IF(D10=0, "Sem dados", IF(J10>=2, "Excelente", IF(J10>=1.5, "Bom", IF(J10>=1, "Regular", "Ruim"))))) | M10: =IF(A10="", 0, J10 + (1000-ROW())/1000000) -> 0
H11: =IF(A11="","",COUNTIFS('Registro de Vendas'!D$5:D$1000, A11)) | I11: =IF(A11="","",IF(H11>0, D11/H11, 0)) | J11: =IF(A11="","",IF(D11>0, SUMIFS('Registro de Vendas'!B$5:B$1000, 'Registro de Vendas'!D$5:D$1000, A11)/D11, 0)) | K11: =IF(A11="","",IF(D11=0, "Sem dados", IF(J11>=2, "Excelente", IF(J11>=1.5, "Bom", IF(J11>=1, "Regular", "Ruim"))))) | M11: =IF(A11="", 0, J11 + (1000-ROW())/1000000) -> 0
H12: =IF(A12="","",COUNTIFS('Registro de Vendas'!D$5:D$1000, A12)) | I12: =IF(A12="","",IF(H12>0, D12/H12, 0)) | J12: =IF(A12="","",IF(D12>0, SUMIFS('Registro de Vendas'!B$5:B$1000, 'Registro de Vendas'!D$5:D$1000, A12)/D12, 0)) | K12: =IF(A12="","",IF(D12=0, "Sem dados", IF(J12>=2, "Excelente", IF(J12>=1.5, "Bom", IF(J12>=1, "Regular", "Ruim"))))) | M12: =IF(A12="", 0, J12 + (1000-ROW())/1000000) -> 0
H13: =IF(A13="","",COUNTIFS('Registro de Vendas'!D$5:D$1000, A13)) | I13: =IF(A13="","",IF(H13>0, D13/H13, 0)) | J13: =IF(A13="","",IF(D13>0, SUMIFS('Registro de Vendas'!B$5:B$1000, 'Registro de Vendas'!D$5:D$1000, A13)/D13, 0)) | K13: =IF(A13="","",IF(D13=0, "Sem dados", IF(J13>=2, "Excelente", IF(J13>=1.5, "Bom", IF(J13>=1, "Regular", "Ruim"))))) | M13: =IF(A13="", 0, J13 + (1000-ROW())/1000000) -> 0
H14: =IF(A14="","",COUNTIFS('Registro de Vendas'!D$5:D$1000, A14)) | I14: =IF(A14="","",IF(H14>0, D14/H14, 0)) | J14: =IF(A14="","",IF(D14>0, SUMIFS('Registro de Vendas'!B$5:B$1000, 'Registro de Vendas'!D$5:D$1000, A14)/D14, 0)) | K14: =IF(A14="","",IF(D14=0, "Sem dados", IF(J14>=2, "Excelente", IF(J14>=1.5, "Bom", IF(J14>=1, "Regular", "Ruim"))))) | M14: =IF(A14="", 0, J14 + (1000-ROW())/1000000) -> 0
H15: =IF(A15="","",COUNTIFS('Registro de Vendas'!D$5:D$1000, A15)) | I15: =IF(A15="","",IF(H15>0, D15/H15, 0)) | J15: =IF(A15="","",IF(D15>0, SUMIFS('Registro de Vendas'!B$5:B$1000, 'Registro de Vendas'!D$5:D$1000, A15)/D15, 0)) | K15: =IF(A15="","",IF(D15=0, "Sem dados", IF(J15>=2, "Excelente", IF(J15>=1.5, "Bom", IF(J15>=1, "Regular", "Ruim"))))) | M15: =IF(A15="", 0, J15 + (1000-ROW())/1000000) -> 0
H16: =IF(A16="","",COUNTIFS('Registro de Vendas'!D$5:D$1000, A16)) | I16: =IF(A16="","",IF(H16>0, D16/H16, 0)) | J16: =IF(A16="","",IF(D16>0, SUMIFS('Registro de Vendas'!B$5:B$1000, 'Registro de Vendas'!D$5:D$1000, A16)/D16, 0)) | K16: =IF(A16="","",IF(D16=0, "Sem dados", IF(J16>=2, "Excelente", IF(J16>=1.5, "Bom", IF(J16>=1, "Regular", "Ruim"))))) | M16: =IF(A16="", 0, J16 + (1000-ROW())/1000000) -> 0
H17: =IF(A17="","",COUNTIFS('Registro de Vendas'!D$5:D$1000, A17)) | I17: =IF(A17="","",IF(H17>0, D17/H17, 0)) | J17: =IF(A17="","",IF(D17>0, SUMIFS('Registro de Vendas'!B$5:B$1000, 'Registro de Vendas'!D$5:D$1000, A17)/D17, 0)) | K17: =IF(A17="","",IF(D17=0, "Sem dados", IF(J17>=2, "Excelente", IF(J17>=1.5, "Bom", IF(J17>=1, "Regular", "Ruim"))))) | M17: =IF(A17="", 0, J17 + (1000-ROW())/1000000) -> 0
H18: =IF(A18="","",COUNTIFS('Registro de Vendas'!D$5:D$1000, A18)) | I18: =IF(A18="","",IF(H18>0, D18/H18, 0)) | J18: =IF(A18="","",IF(D18>0, SUMIFS('Registro de Vendas'!B$5:B$1000, 'Registro de Vendas'!D$5:D$1000, A18)/D18, 0)) | K18: =IF(A18="","",IF(D18=0, "Sem dados", IF(J18>=2, "Excelente", IF(J18>=1.5, "Bom", IF(J18>=1, "Regular", "Ruim"))))) | M18: =IF(A18="", 0, J18 + (1000-ROW())/1000000) -> 0
H19: =IF(A19="","",COUNTIFS('Registro de Vendas'!D$5:D$1000, A19)) | I19: =IF(A19="","",IF(H19>0, D19/H19, 0)) | J19: =IF(A19="","",IF(D19>0, SUMIFS('Registro de Vendas'!B$5:B$1000, 'Registro de Vendas'!D$5:D$1000, A19)/D19, 0)) | K19: =IF(A19="","",IF(D19=0, "Sem dados", IF(J19>=2, "Excelente", IF(J19>=1.5, "Bom", IF(J19>=1, "Regular", "Ruim"))))) | M19: =IF(A19="", 0, J19 + (1000-ROW())/1000000) -> 0
H20: =IF(A20="","",COUNTIFS('Registro de Vendas'!D$5:D$1000, A20)) | I20: =IF(A20="","",IF(H20>0, D20/H20, 0)) | J20: =IF(A20="","",IF(D20>0, SUMIFS('Registro de Vendas'!B$5:B$1000, 'Registro de Vendas'!D$5:D$1000, A20)/D20, 0)) | K20: =IF(A20="","",IF(D20=0, "Sem dados", IF(J20>=2, "Excelente", IF(J20>=1.5, "Bom", IF(J20>=1, "Regular", "Ruim"))))) | M20: =IF(A20="", 0, J20 + (1000-ROW())/1000000) -> 0
H21: =IF(A21="","",COUNTIFS('Registro de Vendas'!D$5:D$1000, A21)) | I21: =IF(A21="","",IF(H21>0, D21/H21, 0)) | J21: =IF(A21="","",IF(D21>0, SUMIFS('Registro de Vendas'!B$5:B$1000, 'Registro de Vendas'!D$5:D$1000, A21)/D21, 0)) | K21: =IF(A21="","",IF(D21=0, "Sem dados", IF(J21>=2, "Excelente", IF(J21>=1.5, "Bom", IF(J21>=1, "Regular", "Ruim"))))) | M21: =IF(A21="", 0, J21 + (1000-ROW())/1000000) -> 0
... H100: =IF(A100="","",COUNTIFS('Registro de Vendas'!D$5:D$1000, A100)) | I100: =IF(A100="","",IF(H100>0, D100/H100, 0)) | J100: =IF(A100="","",IF(D100>0, SUMIFS('Registro de Vendas'!B$5:B$1000, 'Registro de Vendas'!D$5:D$1000, A100)/D100, 0)) | K100: =IF(A100="","",IF(D100=0, "Sem dados", IF(J100>=2, "Excelente", IF(J100>=1.5, "Bom", IF(J100>=1, "Regular", "Ruim"))))) | M100: =IF(A100="", 0, J100 + (1000-ROW())/1000000) -> 0

Sheet Analise de Funil
B2: ANALISE DO FUNIL DE VENDAS
B4: Etapa do Funil | C4: Volume Total | D4: Taxa da Etapa | E4: Taxa Acumulada | F4: Alerta / Diagnostico Operacional
B5: 1. Impressoes | C5: =SUM('Controle Diario'!C:C) -> 94300 | D5: 1 | E5: 1 | F5: Volume de entrada do funil
B6: 2. Cliques no Link | C6: =SUM('Controle Diario'!E) -> #NAME? | D6: =IF(C5>0, C6/C5, 0) -> #NAME? | E6: =IF(C5>0, C6/C5, 0) -> #NAME? | F6: =IF(D6<0.01, _xlfn.UNICHAR(128992) & " Criativo (CTR < 1% indica baixa atratividade)", _xlfn.UNICHAR(128994) & " CTR saudavel nos criativos") -> #NAME?
B7: 3. Visualizacoes da Pagina | C7: =SUM('Controle Diario'!F) -> #NAME? | D7: =IF(C6>0, C7/C6, 0) -> #NAME? | E7: =IF(C5>0, C7/C5, 0) -> #NAME? | F7: =IF(D7<0.7, _xlfn.UNICHAR(128992) & " Carregamento (Queda > 30% - verifique velocidade)", _xlfn.UNICHAR(128994) & " Carregamento saudavel") -> #NAME?
B8: 4. Finalizacoes de Compra | C8: =SUM('Controle Diario'!G) -> #NAME? | D8: =IF(C7>0, C8/C7, 0) -> #NAME? | E8: =IF(C5>0, C8/C5, 0) -> #NAME? | F8: =IF(D8<0.05, _xlfn.UNICHAR(128992) & " Landing Page (conversao para checkout < 5%)", _xlfn.UNICHAR(128994) & " Landing Page saudavel") -> #NAME?
B9: 5. Compras Realizadas | C9: =SUM('Controle Diario'!H) -> #NAME? | D9: =IF(C8>0, C9/C8, 0) -> #NAME? | E9: =IF(C5>0, C9/C5, 0) -> #NAME? | F9: =IF(D9<0.05, _xlfn.UNICHAR(128992) & " Checkout/Oferta (conversao checkout < 5%)", _xlfn.UNICHAR(128994) & " Checkout/Oferta saudavel") -> #NAME?

Sheet Historico de Escala
A2: HISTORICO E REGISTRO DE ESCALA
A4: Data | B4: Campanha | C4: Orcamento Anterior | D4: Novo Orcamento | E4: Percentual de Escala | F4: Motivo da Alteracao | G4: Resultado Apos Escala | H4: Observacoes
A5: 46362 | B5: Campanha Validacao | C5: 50 | D5: 75 | E5: =IF(A5="","",IF(C5>0, (D5-C5)/C5, 0)) -> 0.5 | F5: ROI Alto | G5: Positivo (Manteve ROI) | H5: CPA estavel sob R$ 15
A6: 15/06/2026 | B6: Campanha Validacao | C6: 75 | D6: 100 | E6: =IF(A6="","",IF(C6>0, (D6-C6)/C6, 0)) -> 0.33333333 | F6: ROI Alto | G6: Positivo (Manteve ROI) | H6: Escala vertical bem sucedida
A7: 18/06/2026 | B7: Campanha Validacao | C7: 100 | D7: 120 | E7: =IF(A7="","",IF(C7>0, (D7-C7)/C7, 0)) -> 0.2 | F7: CPA Abaixo da Meta | G7: Neutro (CPA aceitavel) | H7: Subiu orcamento de seguranca
E8: =IF(A8="","",IF(C8>0, (D8-C8)/C8, 0))
E9: =IF(A9="","",IF(C9>0, (D9-C9)/C9, 0))
E10: =IF(A10="","",IF(C10>0, (D10-C10)/C10, 0))
E11: =IF(A11="","",IF(C11>0, (D11-C11)/C11, 0))
E12: =IF(A12="","",IF(C12>0, (D12-C12)/C12, 0))
E13: =IF(A13="","",IF(C13>0, (D13-C13)/C13, 0))
E14: =IF(A14="","",IF(C14>0, (D14-C14)/C14, 0))
E15: =IF(A15="","",IF(C15>0, (D15-C15)/C15, 0))
E16: =IF(A16="","",IF(C16>0, (D16-C16)/C16, 0))
E17: =IF(A17="","",IF(C17>0, (D17-C17)/C17, 0))
E18: =IF(A18="","",IF(C18>0, (D18-C18)/C18, 0))
E19: =IF(A19="","",IF(C19>0, (D19-C19)/C19, 0))
... E100: =IF(A100="","",IF(C100>0, (D100-C100)/C100, 0))

Sheet Registro de Vendas
A2: REGISTRO DE VENDAS | H2: Faturamento Total | I2: Qtd Vendas | J2: Ticket Medio
H3: =SUM(B) -> #NAME? | I3: =COUNT(B) -> 0 | J3: =IF(I3>0, H3/I3, 0) -> 0
A4: Data | B4: Valor da Venda | C4: Produto | D4: Criativo Responsavel | E4: Campanha | F4: Observacoes
A5: 46301 | B5: 47 | C5: Guia Low Ticket | D5: Criativo A - Imagem Oferta | E5: Campanha Validacao
A6: 46301 | B6: 47 | C6: Guia Low Ticket | D6: Criativo A - Imagem Oferta | E6: Campanha Validacao
A7: 46332 | B7: 47 | C7: Guia Low Ticket | D7: Criativo B - Video Gancho 1 | E7: Campanha Validacao
A8: 46332 | B8: 47 | C8: Guia Low Ticket | D8: Criativo B - Video Gancho 1 | E8: Campanha Validacao
A9: 46332 | B9: 47 | C9: Guia Low Ticket | D9: Criativo B - Video Gancho 1 | E9: Campanha Validacao
A10: 46362 | B10: 47 | C10: Guia Low Ticket | D10: Criativo C - Video Unboxing | E10: Campanha Validacao
A11: 46362 | B11: 47 | C11: Guia Low Ticket | D11: Criativo A - Imagem Oferta | E11: Campanha Validacao
A12: 13/06/2026 | B12: 47 | C12: Guia Low Ticket | D12: Criativo D - Imagem Depoimento | E12: Campanha Validacao
A13: 14/06/2026 | B13: 47 | C13: Guia Low Ticket | D13: Criativo E - Video Promocional | E13: Campanha Validacao
A14: 14/06/2026 | B14: 47 | C14: Guia Low Ticket | D14: Criativo B - Video Gancho 1 | E14: Campanha Validacao
A15: 14/06/2026 | B15: 47 | C15: Guia Low Ticket | D15: Criativo B - Video Gancho 1 | E15: Campanha Validacao
A16: 14/06/2026 | B16: 47 | C16: Guia Low Ticket | D16: Criativo E - Video Promocional | E16: Campanha Validacao
A17: 15/06/2026 | B17: 47 | C17: Guia Low Ticket | D17: Criativo B - Video Gancho 1 | E17: Campanha Validacao
A18: 15/06/2026 | B18: 47 | C18: Guia Low Ticket | D18: Criativo A - Imagem Oferta | E18: Campanha Validacao
A19: 15/06/2026 | B19: 47 | C19: Guia Low Ticket | D19: Criativo B - Video Gancho 1 | E19: Campanha Validacao
A20: 15/06/2026 | B20: 47 | C20: Guia Low Ticket | D20: Criativo C - Video Unboxing | E20: Campanha Validacao
A21: 15/06/2026 | B21: 47 | C21: Guia Low Ticket | D21: Criativo B - Video Gancho 1 | E21: Campanha Validacao
A22: 16/06/2026 | B22: 47 | C22: Guia Low Ticket | D22: Criativo A - Imagem Oferta | E22: Campanha Validacao
A23: 16/06/2026 | B23: 47 | C23: Guia Low Ticket | D23: Criativo A - Imagem Oferta | E23: Campanha Validacao
... A43: 19/06/2026 | B43: 47 | C43: Guia Low Ticket | D43: Criativo E - Video Promocional | E43: Campanha Validacao

Sheet Insights Automaticos
B2: INSIGHTS OPERACIONAIS AUTOMATICOS
B4: Area de Analise | C4: Diagnostico | D4: Recomendacao Operacional
B5: CPA vs Meta | C5: =IF('Dashboard Executivo'!D8=0, "Sem dados de vendas.", IF('Dashboard Executivo'!D8<='Dashboard Executivo'!K6, _xlfn.UNICHAR(128994) & " CPA dentro da meta.", _xlfn.UNICHAR(128992) & " CPA acima da meta.")) -> #NAME? | D5: =IF('Dashboard Executivo'!D8=0, "-", IF('Dashboard Executivo'!D8<='Dashboard Executivo'!K6, "Sua aquisicao esta saudavel. Pode manter ou escalar.", "Cuidado! Pause criativos ruins e reduza verba para controlar custos.")) -> #NAME?
B6: ROAS vs Meta | C6: =IF('Dashboard Executivo'!H5=0, "Sem dados de investimento.", IF('Dashboard Executivo'!H5>='Dashboard Executivo'!K5, _xlfn.UNICHAR(128994) & " ROAS dentro da meta.", _xlfn.UNICHAR(128992) & " ROAS abaixo da meta.")) -> #NAME? | D6: =IF('Dashboard Executivo'!H5=0, "-", IF('Dashboard Executivo'!H5>='Dashboard Executivo'!K5, "Operacao lucrativa. Bom momento para escala gradual.", "Trabalhando no vermelho. Revise o preco ou teste novos criativos.")) -> #NAME?
B7: Conversao de Checkout | C7: =IF('Analise de Funil'!D9<0.05, _xlfn.UNICHAR(128992) & " Checkout baixo (<5%)", _xlfn.UNICHAR(128994) & " Checkout saudavel") -> #NAME? | D7: =IF('Analise de Funil'!D9<0.05, "Gargalo no checkout. Use checkout de 1 clique, Pix automatico e recupere abandonos.", "Mantenha a estrutura e continue otimizando.") -> #NAME?
B8: Conversao de Landing Page | C8: =IF('Analise de Funil'!D8<0.05, _xlfn.UNICHAR(128992) & " Landing Page baixa (<5%)", _xlfn.UNICHAR(128994) & " Landing Page saudavel") -> #NAME? | D8: =IF('Analise de Funil'!D8<0.05, "Verifique velocidade e garanta promessa clara na primeira dobra.", "Mantenha e faca testes A/B pontuais.") -> #NAME?
B9: Atratividade dos Criativos | C9: =IF('Analise de Funil'!D6<0.01, _xlfn.UNICHAR(128992) & " CTR baixo (<1%)", _xlfn.UNICHAR(128994) & " CTR saudavel") -> #NAME? | D9: =IF('Analise de Funil'!D6<0.01, "Produza criativos com hooks (ganchos) de 3 segundos mais fortes.", "Parabens! Continue produzindo variacoes dos melhores.") -> #NAME?
B10: Tendencia de CPA | C10: =IF(COUNTA('Controle Diario'!A$5:A$100)<7, "Historico insuficiente.", IF(AND(INDEX('Controle Diario'!L$5:L$100, COUNTA('Controle Diario'!A$5:A$100)) > INDEX('Controle Diario'!L$5:L$100, COUNTA('Controle Diario'!A$5:A$100)-1), INDEX('Controle Diario'!L$5:L$100, COUNTA('Controle Diario'!A$5:A$100)-1) > INDEX('Controle Diario'!L$5:L$100, COUNTA('Controle Diario'!A$5:A$100)-2)), _xlfn.UNICHAR(128992) & " CPA subindo ha 3 dias", _xlfn.UNICHAR(128994) & " CPA saudavel/estavel")) -> 🟢 CPA saudavel/estavel | D10: =IF(COUNTA('Controle Diario'!A$5:A$100)<7, "-", IF(AND(INDEX('Controle Diario'!L$5:L$100, COUNTA('Controle Diario'!A$5:A$100)) > INDEX('Controle Diario'!L$5:L$100, COUNTA('Controle Diario'!A$5:A$100)-1), INDEX('Controle Diario'!L$5:L$100, COUNTA('Controle Diario'!A$5:A$100)-1) > INDEX('Controle Diario'!L$5:L$100, COUNTA('Controle Diario'!A$5:A$100)-2)), "Fadiga de criativo provavel. Renove os anuncios do conjunto.", "Normalidade operacional mantida.")) -> Normalidade operacional mantida.
B11: Criativo Destaque | C11: =_xlfn.UNICHAR(127942) & " Criativo: " & 'Controle de Criativos'!P6 -> 🏆 Criativo: Criativo B - Video Gancho 1 | D11: =CONCATENATE("ROAS de ", TEXT('Controle de Criativos'!Q6, "0.0"), ". Considere criar variacoes do mesmo.") -> ROAS de 02. Considere criar variacoes do mesmo.
